veriftools/__init__.py
veriftools/veriftools.py
veriftools-2.0.0.dist-info/LICENSE
veriftools-2.0.0.dist-info/METADATA
veriftools-2.0.0.dist-info/WHEEL
veriftools-2.0.0.dist-info/top_level.txt
veriftools-2.0.0.dist-info/RECORD
