Metadata-Version: 2.1
Name: veriftools
Version: 2.0.0
Summary: Package for generating images
Home-page: https://github.com
Author: Martin
Author-email: veriftools@gmail.com
License: UNKNOWN
Project-URL: Bug Tracker, https://github.com
Platform: UNKNOWN
Classifier: Programming Language :: Python :: 3
Classifier: License :: OSI Approved :: MIT License
Classifier: Operating System :: OS Independent
Requires-Python: >=3.7
Requires-Dist: requests (>=2.21.0)
